noseapp_workspace
tests
