Metadata-Version: 1.1
Name: noseapp-workspace
Version: 0.4.0
Summary: workspace extension for noseapp lib
Home-page: https://github.com/trifonovmixail/noseapp_workspace
Author: Mikhail Trifonov
Author-email: mikhail.trifonov@corp.mail.ru
License: UNKNOWN
Platform: any
Classifier: Development Status :: 4 - Beta
Classifier: Intended Audience :: Developers
Classifier: Operating System :: OS Independent
Classifier: Programming Language :: Python
Classifier: Programming Language :: Python :: 2.7
Classifier: Topic :: Software Development :: Testing
